{
    "variants": {
        "facing=north,filled=false": {"model": "cfm:counter_sink_pre_old", "y": 270 },
        "facing=east,filled=false": {"model": "cfm:counter_sink_pre_old" },
        "facing=south,filled=false": {"model": "cfm:counter_sink_pre_old", "y": 90 },
        "facing=west,filled=false": {"model": "cfm:counter_sink_pre_old", "y": 180 },
        "facing=north,filled=true": {"model": "cfm:counter_sink_filled_pre_old", "y": 270 },
        "facing=east,filled=true": {"model": "cfm:counter_sink_filled_pre_old" },
        "facing=south,filled=true": {"model": "cfm:counter_sink_filled_pre_old", "y": 90 },
        "facing=west,filled=true": {"model": "cfm:counter_sink_filled_pre_old", "y": 180 }
    }
}